README.rst
setup.py
inipgdump/__init__.py
inipgdump/core.py
inipgdump.egg-info/PKG-INFO
inipgdump.egg-info/SOURCES.txt
inipgdump.egg-info/dependency_links.txt
inipgdump.egg-info/entry_points.txt
inipgdump.egg-info/top_level.txt