Metadata-Version: 1.0
Name: inipgdump
Version: 0.2.2
Summary: Creates a dump of the PostgreSQL database. Stores the specified number of dumps, deletes the old dumps.
Home-page: https://github.com/xtimon/inipgdump
Author: Timur Isanov
Author-email: tisanov@yahoo.com
License: MIT
Platform: UNKNOWN
